transwarp_embedding_hub/__init__.py
transwarp_embedding_hub/azure.py
transwarp_embedding_hub/base_embedding.py
transwarp_embedding_hub/config.yaml
transwarp_embedding_hub/embedding_hub.py
transwarp_embedding_hub/openai.py
transwarp_embedding_hub/pulse.py
transwarp_embedding_hub/text_segmentation.py
transwarp_hippo_api/__init__.py
transwarp_hippo_api/conn_mgr.py
transwarp_hippo_api/hippo_client.py
transwarp_hippo_api/hippo_type.py
transwarp_hippo_api/private_embedding.py
transwarp_hippo_langchain/__init__.py
transwarp_hippo_langchain/embedding_hub_langchain.py
transwarp_hippo_langchain/hippo_langchain.py
hippo_api-1.2.0.dist-info/METADATA
hippo_api-1.2.0.dist-info/WHEEL
hippo_api-1.2.0.dist-info/top_level.txt
hippo_api-1.2.0.dist-info/RECORD
