Metadata-Version: 2.1
Name: hippo-api
Version: 1.2.0
Summary: Transwarp Hippo API
Author: transwarp
Requires-Python: >=3.8.0
